simple_logging_interceptor/__init__.py
simple_logging_interceptor/decorators.py
simple_logging_interceptor/parser.py
simple_logging_interceptor-0.1.6.dist-info/METADATA
simple_logging_interceptor-0.1.6.dist-info/WHEEL
simple_logging_interceptor-0.1.6.dist-info/top_level.txt
simple_logging_interceptor-0.1.6.dist-info/RECORD
