Metadata-Version: 2.4
Name: simple-logging-interceptor
Version: 0.1.6
Summary: A simple Python decorator for logging function calls, arguments, return values, execution time, and exceptions.
Author: Mahmoud Samir
Author-email: mahmoudsamir8998@gmail.com
License: MIT
Classifier: Programming Language :: Python :: 3
Classifier: License :: OSI Approved :: MIT License
Classifier: Operating System :: OS Independent
Requires-Python: >=3.8
Dynamic: author
Dynamic: author-email
Dynamic: classifier
Dynamic: description
Dynamic: description-content-type
Dynamic: license
Dynamic: requires-python
Dynamic: summary
